README.md
setup.cfg
setup.py
morsepy/__init__.py
morsepy/morsepy.py
morsepy.egg-info/PKG-INFO
morsepy.egg-info/SOURCES.txt
morsepy.egg-info/dependency_links.txt
morsepy.egg-info/top_level.txt