Metadata-Version: 2.1
Name: morsepy
Version: 0.3.2
Summary: A morse decrypter and encrypter module for python
Home-page: https://github.com/silas-hw/Morsepy
Author: silas-hw
Author-email: silas.hayes.williams@gmail.com
License: MIT
Download-URL: https://github.com/silas-hw/Morsepy/archive/v0.3.2.tar.gz
Keywords: morse,decrypt,encrypt
Platform: UNKNOWN
Classifier: Development Status :: 3 - Alpha
Classifier: Intended Audience :: Developers
Classifier: Topic :: Software Development :: Build Tools
Classifier: License :: OSI Approved :: MIT License
Classifier: Programming Language :: Python :: 3
Classifier: Programming Language :: Python :: 3.4
Classifier: Programming Language :: Python :: 3.5
Classifier: Programming Language :: Python :: 3.6
Classifier: Programming Language :: Python :: 3.7
Classifier: Programming Language :: Python :: 3.8
